{"nodes": [{"id": "consumers_src_phash_ts", "label": "phash.ts", "file_type": "code", "source_file": "consumers/src/phash.ts", "source_location": "L1"}, {"id": "phash_perceptualhash", "label": "perceptualHash()", "file_type": "code", "source_file": "consumers/src/phash.ts", "source_location": "L23"}, {"id": "phash_bands", "label": "bands()", "file_type": "code", "source_file": "consumers/src/phash.ts", "source_location": "L85"}, {"id": "phash_hamming", "label": "hamming()", "file_type": "code", "source_file": "consumers/src/phash.ts", "source_location": "L90"}], "edges": [{"source": "consumers_src_phash_ts", "target": "photon", "relation": "imports_from", "confidence": "EXTRACTED", "source_file": "consumers/src/phash.ts", "source_location": "L7", "weight": 1.0}, {"source": "consumers_src_phash_ts", "target": "phash_perceptualhash", "relation": "contains", "confidence": "EXTRACTED", "source_file": "consumers/src/phash.ts", "source_location": "L23", "weight": 1.0}, {"source": "consumers_src_phash_ts", "target": "phash_bands", "relation": "contains", "confidence": "EXTRACTED", "source_file": "consumers/src/phash.ts", "source_location": "L85", "weight": 1.0}, {"source": "consumers_src_phash_ts", "target": "phash_hamming", "relation": "contains", "confidence": "EXTRACTED", "source_file": "consumers/src/phash.ts", "source_location": "L90", "weight": 1.0}], "raw_calls": [{"caller_nid": "phash_perceptualhash", "callee": "new_from_byteslice", "source_file": "consumers/src/phash.ts", "source_location": "L27"}, {"caller_nid": "phash_perceptualhash", "callee": "resize", "source_file": "consumers/src/phash.ts", "source_location": "L28"}, {"caller_nid": "phash_perceptualhash", "callee": "get_raw_pixels", "source_file": "consumers/src/phash.ts", "source_location": "L29"}, {"caller_nid": "phash_perceptualhash", "callee": "push", "source_file": "consumers/src/phash.ts", "source_location": "L56"}, {"caller_nid": "phash_perceptualhash", "callee": "sort", "source_file": "consumers/src/phash.ts", "source_location": "L61"}, {"caller_nid": "phash_perceptualhash", "callee": "slice", "source_file": "consumers/src/phash.ts", "source_location": "L61"}, {"caller_nid": "phash_perceptualhash", "callee": "floor", "source_file": "consumers/src/phash.ts", "source_location": "L62"}, {"caller_nid": "phash_perceptualhash", "callee": "toString", "source_file": "consumers/src/phash.ts", "source_location": "L73"}, {"caller_nid": "phash_perceptualhash", "callee": "free", "source_file": "consumers/src/phash.ts", "source_location": "L79"}, {"caller_nid": "phash_perceptualhash", "callee": "free", "source_file": "consumers/src/phash.ts", "source_location": "L80"}, {"caller_nid": "phash_bands", "callee": "slice", "source_file": "consumers/src/phash.ts", "source_location": "L86"}, {"caller_nid": "phash_bands", "callee": "slice", "source_file": "consumers/src/phash.ts", "source_location": "L86"}, {"caller_nid": "phash_bands", "callee": "slice", "source_file": "consumers/src/phash.ts", "source_location": "L86"}, {"caller_nid": "phash_bands", "callee": "slice", "source_file": "consumers/src/phash.ts", "source_location": "L86"}, {"caller_nid": "phash_hamming", "callee": "parseInt", "source_file": "consumers/src/phash.ts", "source_location": "L94"}, {"caller_nid": "phash_hamming", "callee": "parseInt", "source_file": "consumers/src/phash.ts", "source_location": "L94"}]}